README.md
setup.py
intranet_infiltrator/__init__.py
intranet_infiltrator/infiltrator.py
intranet_infiltrator/infiltrator31ms.py
skitarii.egg-info/PKG-INFO
skitarii.egg-info/SOURCES.txt
skitarii.egg-info/dependency_links.txt
skitarii.egg-info/requires.txt
skitarii.egg-info/top_level.txt
util/__init__.py
util/dates.py
util/logger.py