Metadata-Version: 2.1
Name: skitarii
Version: 0.0.3
Summary: automata for routine
Home-page: https://github.com/roventine/skitarii
Author: roventine
Author-email: ukyotachibana@yeah.net
License: UNKNOWN
Platform: UNKNOWN
Classifier: Programming Language :: Python :: 3
Classifier: License :: OSI Approved :: MIT License
Classifier: Operating System :: OS Independent
Requires-Python: >=3.6
